stock_options_python-0.1.0.dist-info/METADATA
stock_options_python-0.1.0.dist-info/WHEEL
stock_options_python-0.1.0.dist-info/licenses/LICENSE
stock_options_python/__init__.py
stock_options_python/stock_options_python.cpython-39-powerpc64le-linux-gnu.so
stock_options_python-0.1.0.dist-info/RECORD
