Metadata-Version: 2.4
Name: stock-options-python
Version: 0.1.0
Classifier: Development Status :: 4 - Beta
Classifier: Intended Audience :: Financial and Insurance Industry
Classifier: Intended Audience :: Developers
Classifier: License :: OSI Approved :: BSD License
Classifier: Programming Language :: Python :: 3
Classifier: Programming Language :: Python :: 3.8
Classifier: Programming Language :: Python :: 3.9
Classifier: Programming Language :: Python :: 3.10
Classifier: Programming Language :: Python :: 3.11
Classifier: Programming Language :: Python :: 3.12
Classifier: Programming Language :: Rust
Classifier: Topic :: Office/Business :: Financial :: Investment
License-File: LICENSE
Summary: Fast option pricing Greeks calculations using Black-Scholes and Bjerksund-Stensland models
Keywords: finance,options,black-scholes,greeks,derivatives,trading
License: BSD-3-Clause
Requires-Python: >=3.8
Project-URL: Homepage, https://github.com/ajokela/stock-options-python
Project-URL: Repository, https://github.com/ajokela/stock-options-python
